bleson/__init__.py
bleson/__main__.py
bleson/logger.py
bleson/beacons/__init__.py
bleson/beacons/eddystone.py
bleson/core/__init__.py
bleson/core/roles.py
bleson/core/types.py
bleson/core/hci/__init__.py
bleson/core/hci/constants.py
bleson/core/hci/type_converters.py
bleson/core/hci/types.py
bleson/interfaces/__init__.py
bleson/interfaces/adapter.py
bleson/interfaces/provider.py
bleson/interfaces/role.py
bleson/providers/__init__.py
bleson/providers/linux/__init__.py
bleson/providers/linux/constants.py
bleson/providers/linux/linux_adapter.py
bleson/providers/linux/linux_provider.py
bleson/providers/macos/__init__.py
bleson/providers/macos/macos_adapter.py
bleson/providers/macos/macos_provider.py
bleson/providers/win32/__init__.py
bleson/providers/win32/win32_adapter.py
bleson/providers/win32/win32_provider.py
bleson-0.0.6.dist-info/DESCRIPTION.rst
bleson-0.0.6.dist-info/METADATA
bleson-0.0.6.dist-info/RECORD
bleson-0.0.6.dist-info/WHEEL
bleson-0.0.6.dist-info/metadata.json
bleson-0.0.6.dist-info/top_level.txt
