Metadata-Version: 2.0
Name: bleson
Version: 0.0.6
Summary: Bluetooth LE Library
Home-page: https://github.com/TheCellule/python-bleson
Author: TheCellule
Author-email: thecellule@gmail.com
License: MIT
Platform: UNKNOWN
Requires-Dist: blesonwin
